acsylla/__init__.py
acsylla/base.py
acsylla/errors.py
acsylla/factories.py
acsylla/version.py
acsylla/_cython/cyacsylla.cpython-38-darwin.so
acsylla-1.0.0.dist-info/METADATA
acsylla-1.0.0.dist-info/WHEEL
acsylla-1.0.0.dist-info/top_level.txt
acsylla-1.0.0.dist-info/RECORD
