Metadata-Version: 2.1
Name: acsylla
Version: 1.0.0
Summary: A high performance asynchronous Cassandra and ScyllaDB client
Home-page: http://github.com/acsylla/acsylla
Author: Pau Freixes
Author-email: pfreixes@gmail.com
Platform: *nix
Classifier: Development Status :: 5 - Production/Stable
Classifier: Programming Language :: Python :: 3 :: Only
Classifier: Programming Language :: Python :: 3.8
Classifier: Programming Language :: Python :: 3.9
Classifier: Programming Language :: Python :: 3.10
Classifier: Programming Language :: Python :: 3.11
Classifier: Programming Language :: Python :: 3.12
Classifier: Programming Language :: Python :: 3.13
Classifier: License :: OSI Approved :: Apache Software License
Classifier: License :: OSI Approved :: MIT License
Classifier: Intended Audience :: Developers
Provides-Extra: dev
Requires-Dist: Cython; extra == "dev"
Requires-Dist: pytest==6.2.5; extra == "dev"
Requires-Dist: pytest-mock==3.6.1; extra == "dev"
Requires-Dist: pytest-asyncio==0.16.0; extra == "dev"
Requires-Dist: asynctest==0.13.0; extra == "dev"
Requires-Dist: pytest-cov==3.0.0; extra == "dev"
Requires-Dist: black==22.8.0; extra == "dev"
Requires-Dist: click==8.1.3; extra == "dev"
Requires-Dist: isort==5.9.3; extra == "dev"
Requires-Dist: flake8==4.0.1; extra == "dev"
Requires-Dist: mypy==0.910; extra == "dev"
Requires-Dist: setuptools; extra == "dev"
